CHANGELOG.md
LICENSE
craft_ai/__init__.py
craft_ai/client.py
craft_ai/constants.py
craft_ai/errors.py
craft_ai/formatters.py
craft_ai/helpers.py
craft_ai/interpreter.py
craft_ai/interpreter_v1.py
craft_ai/interpreter_v2.py
craft_ai/jwt_decode.py
craft_ai/operators.py
craft_ai/pandas/__init__.py
craft_ai/pandas/client.py
craft_ai/pandas/constants.py
craft_ai/pandas/interpreter.py
craft_ai/pandas/utils.py
craft_ai/reducer.py
craft_ai/time.py
craft_ai/timezones.py
craft_ai/tree_utils.py
craft_ai/types.py
craft_ai/websocket_client.py
craft_ai-2.4.3.dist-info/LICENSE
craft_ai-2.4.3.dist-info/WHEEL
craft_ai-2.4.3.dist-info/METADATA
craft_ai-2.4.3.dist-info/RECORD
