Metadata-Version: 2.1
Name: craft-ai
Version: 2.4.3
Summary: craft ai API python 3 client
Home-page: https://craft.ai
License: BSD-3-Clause
Keywords: ai,craft-ai
Author: craft ai
Author-email: contact@craft.ai
Requires-Python: >=3.6.1,<4.0.0
Classifier: Development Status :: 5 - Production/Stable
Classifier: Intended Audience :: Developers
Classifier: License :: OSI Approved :: BSD License
Classifier: Programming Language :: Python :: 3
Classifier: Programming Language :: Python :: 3.7
Classifier: Programming Language :: Python :: 3.8
Classifier: Programming Language :: Python :: 3.9
Classifier: Topic :: Scientific/Engineering :: Artificial Intelligence
Provides-Extra: pandas
Requires-Dist: nest-asyncio (>=1.5.1,<2.0.0)
Requires-Dist: pandas (>=1.0.1,<2.0.0); extra == "pandas"
Requires-Dist: pytest (>=5.4.3,<6.0.0)
Requires-Dist: pytest-subtests (>=0.3.1,<0.4.0)
Requires-Dist: python-dateutil (>=2.8.1,<3.0.0)
Requires-Dist: requests (>=2.20.1,<3.0.0)
Requires-Dist: semver (>=2.10.2,<3.0.0)
Requires-Dist: tzlocal (>=1.2.2,<2.0.0)
Requires-Dist: websockets (>=9.1,<10.0)
Project-URL: Repository, https://github.com/craft-ai/craft-ai-client-python/
